pyqtws/__init__.py
pyqtws/chooser_window.py
pyqtws/config.py
pyqtws/main.py
pyqtws/options_window.py
pyqtws/permissions.py
pyqtws/plugins.py
pyqtws/silo_window.py
pyqtws/web.py
pyqtws/apps/__init__.py
pyqtws/desktops/__init__.py
pyqtws/icons/__init__.py
pyqtws/plugin/ChangeUserAgent.py
pyqtws/plugin/FloatingWindow.py
pyqtws/plugin/GoogleAuthentication.py
pyqtws/plugin/Multimedia.py
pyqtws/plugin/Notifications.py
pyqtws/plugin/TrayIcon.py
pyqtws/plugin/WebRTC.py
pyqtws/plugin/__init__.py
pyqtws-0.1.47.data/scripts/silo
pyqtws-0.1.47.dist-info/LICENSE
pyqtws-0.1.47.dist-info/METADATA
pyqtws-0.1.47.dist-info/WHEEL
pyqtws-0.1.47.dist-info/top_level.txt
pyqtws-0.1.47.dist-info/RECORD
