Metadata-Version: 2.1
Name: pyqtws
Version: 0.1.47
Summary: Standalone website wrapper
Home-page: http://github.com/intersimone999/pyqtws
Author: Simone Scalabrino
Author-email: simone@datasound.it
License: MIT
Platform: UNKNOWN
Requires-Dist: PyQt5
Requires-Dist: PyQtWebEngine
Requires-Dist: dbus-python
Requires-Dist: pygi
Requires-Dist: pystray
